{
	"current-version":
	{
		"version-1.0.0": 2,
		"version-1.0.0b": 3,
		"version-1.0.1": 1,
	},
	"update-message": "The Randomness Levels Update Checker Test!",
	"update-message-1": "New Major Version Released.",
	"update-message-2": "New Version Released.",
	"update-message-3": "New Minor Version Released.",
	"update-message-4": "New Beta Build Released.",
	"update-message-5": "New Preview Build Released.",
	"update-message-6": "New Patch Released.",
	"update-message-7": "New Hotfix Released.",
	"update-url-page": "https://github.com/PizzaLuigi647/Super-Mario-Bros-The-Randomness-Levels/releases",
        "update-version-name": "The Randomness Levels - Update Checker Test"
}
